[
    {
        "title": "Капитальный ремонт квартир",
        "price": "6000",
        "TitleDesign": "Капитальный ремонт квартир от Проект Монтаж",
        "DescrDesign": "Кардинальное изменение квартиры с применением отделочных материалов высокого качества и современного оборудования. Вам не придется решать вопросы, связанные с ремонтом. Мы самостоятельно организуем поставки всех отделочных материалов, вывезем весь мусор, решим все вопросы с управляющей компанией.",
        "TimeTitle": "Сроки проведения капитального ремонта",
        "TimeMetr1": "до 48 м2",
        "TimeMetr2": "до 70 м2",
        "TimeMetr3": "до 100 м2",
        "TimeMetr4": "до 140 м2",
        "TextMetr1": "30-60 дней",
        "TextMetr2": "60-90 дней",
        "TextMetr3": "90-160 дней",
        "TextMetr4": "160-280 дней",
        "items": [
            {
                "ItemsTitle": "Работы со стенами",
                "item": [
                    "Демонтаж старых покрытий",
                    "Грунтовка стен",
                    "Штукатурка стен по маякам",
                    "Поклейка малярной сетки",
					"Шпаклевка стен",
					"Монтаж фальшстен из ГКЛ",
					"Поклейка обоев"
                ]
            }, 
            {
                "ItemsTitle": "Работы с полами",
                "item": [
                    "Демонтаж старого напольного покрытия",
                    "Устройство стяжки",
                    "Устройство гидроизоляции в мокрых зонах",
                    "Кладка керамогранита",
                    "Укладка ламината или паркетной доски",
					"Монтаж напольного плинтуса"
                ]
            }, 
            {
                "ItemsTitle": "Работы с потолком",
                "item": [
                    "Демонтаж старых покрытий",
                    "Грунтовка потолка",
                    "Выравнивание по плоскости",
					"Шпаклевка и шлифовка",
					"Покраска два слоя",
					"Монтаж потолочного плинтуса",
					"Монтаж натяжного потолка"
                ]
            }, 
            {
                "ItemsTitle": "Электромонтажные работы",
                "item": [
                    "ЗШтробление под электропровод",
                    "Сверление отверстий для розеток и выключателей",
                    "Прокладка электропровода в гофре",
					"Прокладка слаботочного провода в гофре",
					"Установка электрощита",
					"Установка розеток и выключателей",
					"Установка люстр, бра, светильников"
                ]
            }, 
            {
                "ItemsTitle": "Сантехнические работы",
                "item": [
                    "Демонтаж сантехнического оборудования",
                    "Установка фильтров грубой очистки",
                    "Установка коллекторов для подачи воды",
					"Комплексная разводка сантехнических труб",
					"Установка сантехнического оборудования"
                ]
            }
        ]
    }
  ]