[
    {
        "title": "Элитный ремонт квартир",
        "price": "12000",
        "TitleDesign": "Элитный ремонт квартир под ключ в Москве и области",
        "DescrDesign": "Компания Проект Монтаж использует эксклюзивные отделочные материалы, неповторимые дизайнерские решение, узкопрофильные мастера готовы выполнить все работы точно в срок без привлечения сторонних подрядчиков. Заказав у нас элитный ремонт наши клиенты получают самый лучший сервис в сфере ремонта. Персональный прораб, согласование и комплектация решение всех проблем все в одном месте, еженедельно фото видео отчет, узкопрофильные мастера у комплектованы современным инструментом.",
        "TimeTitle": "Сроки проведения элитного ремонта",
        "TimeMetr1": "до 48 м2",
        "TimeMetr2": "до 70 м2",
        "TimeMetr3": "до 100 м2",
        "TimeMetr4": "до 140 м2",
        "TextMetr1": "70-110 дней",
        "TextMetr2": "100-145 дней",
        "TextMetr3": "145-195 дней",
        "TextMetr4": "195-235 дней",
        "items": [
            {
                "ItemsTitle": "Работы со стенами",
                "item": [
                    "Демонтажные работы",
                    "Монтаж перегородок",
                    "Устройство и усиление дверных проемов",
                    "Грунтовка стен",
					"Поклейка малярной сетки",
					"Штукатурка стен по маякам",
					"Устройство звукоизоляции",
					"Устройство ниш из ГКЛ",
					"Шпаклевка стен",
					"Покраска стен",
					"Нанесение декоративной штукатурки",
					"Поклейка дизайнерских обоев",
					"Кладка мрамора",
					"Кладка мозаики",
					"Монтаж лепнины",
					"Работы с потолками"
                ]
            }, 
            {
                "ItemsTitle": "Работы с полами",
                "item": [
                    "Демонтаж старых покрытий",
                    "Устройство стяжки",
                    "Монтаж звукоизоляции",
                    "Укладка армированной металлической сетки",
                    "Устройство гидроизоляции",
					"Кладка плитки, керамогранита",
					"Укладка ламината, паркетной доски",
					"Монтаж напольного плинтуса"
                ]
            }, 
            {
                "ItemsTitle": "Работы с потолками",
                "item": [
                    "Грунтовка потолка",
                    "Поклейка малярной сетки",
                    "Штукатурка потолка по маякам",
					"Устройство многоуровневых потолков из ГКЛ",
					"Монтаж лепнины",
					"Монтаж потолочного плинтуса",
					"Звукоизоляция потолка",
					"Шпаклевка потолка",
					"Покраска потолка",
					"Работы с полами"
                ]
            }, 
            {
                "ItemsTitle": "Электромонтажные работы",
                "item": [
                    "Штробление под электропровод",
                    "Сверление отверстий для розеток и выключателей",
                    "Установка электрощита",
					"Укладка электропровода в гофре",
                    "Монтаж слаботочной проводки",
                    "Установка электроприборов розеток и выключателей",
					"Установка люстр, бра, светильников",
					"Установка видеодомофона"
                ]
            }, 
            {
                "ItemsTitle": "Сантехнические работы",
                "item": [
                    "Установка коллекторов для подачи воды",
                    "Установка датчиков от протечки воды",
                    "Установка редукторов давления",
					"Комплексная разводка сантехнических труб",
					"Установка сантехнического оборудования",
					"Установка бойлера"
                ]
            }
        ]
    }
  ]